doorloop_cjmcfaul/__init__.py
doorloop_cjmcfaul/accounts.py
doorloop_cjmcfaul/base.py
doorloop_cjmcfaul/communications.py
doorloop_cjmcfaul/expenses.py
doorloop_cjmcfaul/files.py
doorloop_cjmcfaul/lease_charges.py
doorloop_cjmcfaul/lease_credits.py
doorloop_cjmcfaul/lease_payments.py
doorloop_cjmcfaul/lease_returned_payments.py
doorloop_cjmcfaul/leases.py
doorloop_cjmcfaul/main.py
doorloop_cjmcfaul/notes.py
doorloop_cjmcfaul/owners.py
doorloop_cjmcfaul/portfolios.py
doorloop_cjmcfaul/properties.py
doorloop_cjmcfaul/reports.py
doorloop_cjmcfaul/tasks.py
doorloop_cjmcfaul/tenants.py
doorloop_cjmcfaul/units.py
doorloop_cjmcfaul/users.py
doorloop_cjmcfaul/vendor_bills.py
doorloop_cjmcfaul/vendor_credits.py
doorloop_cjmcfaul/vendors.py
doorloop_cjmcfaul-0.0.1.dist-info/METADATA
doorloop_cjmcfaul-0.0.1.dist-info/WHEEL
doorloop_cjmcfaul-0.0.1.dist-info/licenses/LICENSE
doorloop_cjmcfaul-0.0.1.dist-info/RECORD
