Metadata-Version: 2.1
Name: doorloop_cjmcfaul
Version: 0.0.1
Summary: This library provides a pure python interface to interact with the DoorLoop API
Project-URL: Homepage, https://github.com/cjmcfaul/doorloop
Project-URL: Bugtracker, https://github.com/cjmcfaul/doorloop/issues
Project-URL: Documentation, https://api.doorloop.com/reference/introduction
Author-email: Colin McFaul <colinjmcfaul@gmail.com>
License: Copyright (c) 2022 Colin J. McFaul
Classifier: License :: OSI Approved :: MIT License
Classifier: Operating System :: OS Independent
Classifier: Programming Language :: Python :: 3
Requires-Python: >=3.9
